easy_tf_log.py
easy_tf_log-1.12.dist-info/LICENSE
easy_tf_log-1.12.dist-info/METADATA
easy_tf_log-1.12.dist-info/WHEEL
easy_tf_log-1.12.dist-info/top_level.txt
easy_tf_log-1.12.dist-info/RECORD
