Metadata-Version: 2.1
Name: easy-tf-log
Version: 1.12
Summary: TensorFlow logging made easy
Home-page: https://github.com/mrahtz/easy-tf-log
Author: Matthew Rahtz
Author-email: matthew.rahtz@gmail.com
License: UNKNOWN
Keywords: tensorflow graph graphs graphing
Platform: UNKNOWN
Requires-Dist: numpy
